plind/__init__.py
plind/plmodel.py
plind/contour/__init__.py
plind/contour/core.py
plind/contour_dict/__init__.py
plind/contour_dict/core.py
plind/convergence/__init__.py
plind/convergence/convergence.py
plind/descend/__init__.py
plind/descend/core.py
plind/helpers/__init__.py
plind/helpers/core.py
plind/integrate/__init__.py
plind/integrate/core.py
plind/plexception/__init__.py
plind/plexception/plexception.py
plind/visualize/__init__.py
plind/visualize/core.py
plind-0.1.0.dist-info/LICENSE
plind-0.1.0.dist-info/METADATA
plind-0.1.0.dist-info/WHEEL
plind-0.1.0.dist-info/top_level.txt
plind-0.1.0.dist-info/RECORD
