Metadata-Version: 2.1
Name: plind
Version: 0.1.0
Summary: Picard-Lefschetz Integration in N-Dimensions for highly oscillatory functions
Author-email: Dylan Jow <djow@physics.utoronto.ca>, Fang Xi Lin <hi@fxl.ai>, Emily Tyhurst <tyhurste@gmail.com>
License: GNU GENERAL PUBLIC LICENSE
Project-URL: repository, https://github.com/dljow/plind
Classifier: Programming Language :: Python :: 3
Classifier: License :: OSI Approved :: GNU General Public License v3 (GPLv3)
Classifier: Operating System :: OS Independent
Requires-Python: >=3.8
License-File: LICENSE
Requires-Dist: numpy >=1.0
Requires-Dist: scipy >=1.0
Requires-Dist: matplotlib >=3.0
Requires-Dist: sympy >=1.0
